{
  "useAbortController": true,
  "useAsync": true,
  "useClickOutside": true,
  "useCopyToClipboard": true,
  "useDebounce": true,
  "useDraggable": false,
  "useEventCallback": true,
  "useEventListener": true,
  "useFavicon": false,
  "useHash": false,
  "useIdle": true,
  "useIntersectionObserver": true,
  "useInterval": true,
  "useLatest": true,
  "useLocalStorage": true,
  "useLockBodyScroll": true,
  "useMediaQuery": true,
  "useMountedState": true,
  "useMutationObserver": true,
  "useOnMount": true,
  "usePageVisibility": true,
  "usePrevious": true,
  "useRafState": true,
  "useResizeObserver": true,
  "useScript": true,
  "useSessionStorage": true,
  "useTextareaAutoSize": true,
  "useThrottle": true,
  "useTimeout": true,
  "useTitle": true,
  "useToggle": true,
  "useWindowSize": true
}
